fastapi/__init__.py
fastapi/applications.py
fastapi/background.py
fastapi/concurrency.py
fastapi/datastructures.py
fastapi/encoders.py
fastapi/exception_handlers.py
fastapi/exceptions.py
fastapi/logger.py
fastapi/param_functions.py
fastapi/params.py
fastapi/requests.py
fastapi/responses.py
fastapi/routing.py
fastapi/staticfiles.py
fastapi/templating.py
fastapi/testclient.py
fastapi/types.py
fastapi/utils.py
fastapi/websockets.py
fastapi/dependencies/__init__.py
fastapi/dependencies/models.py
fastapi/dependencies/utils.py
fastapi/middleware/__init__.py
fastapi/middleware/cors.py
fastapi/middleware/gzip.py
fastapi/middleware/httpsredirect.py
fastapi/middleware/trustedhost.py
fastapi/middleware/wsgi.py
fastapi/openapi/__init__.py
fastapi/openapi/constants.py
fastapi/openapi/docs.py
fastapi/openapi/models.py
fastapi/openapi/utils.py
fastapi/security/__init__.py
fastapi/security/api_key.py
fastapi/security/base.py
fastapi/security/http.py
fastapi/security/oauth2.py
fastapi/security/open_id_connect_url.py
fastapi/security/utils.py
tests/__init__.py
tests/main.py
tests/test_additional_properties.py
tests/test_additional_response_extra.py
tests/test_additional_responses_bad.py
tests/test_additional_responses_custom_model_in_callback.py
tests/test_additional_responses_custom_validationerror.py
tests/test_additional_responses_default_validationerror.py
tests/test_additional_responses_response_class.py
tests/test_additional_responses_router.py
tests/test_application.py
tests/test_callable_endpoint.py
tests/test_custom_route_class.py
tests/test_custom_schema_fields.py
tests/test_custom_swagger_ui_redirect.py
tests/test_datastructures.py
tests/test_datetime_custom_encoder.py
tests/test_default_response_class.py
tests/test_default_response_class_router.py
tests/test_dependency_cache.py
tests/test_dependency_class.py
tests/test_dependency_contextmanager.py
tests/test_dependency_duplicates.py
tests/test_dependency_overrides.py
tests/test_dependency_security_overrides.py
st1mulol_fastapi-0.70.0.dist-info/LICENSE
st1mulol_fastapi-0.70.0.dist-info/METADATA
st1mulol_fastapi-0.70.0.dist-info/WHEEL
st1mulol_fastapi-0.70.0.dist-info/top_level.txt
st1mulol_fastapi-0.70.0.dist-info/RECORD
